MANIFEST.in
Makefile
README.md
setup.py
data/egm96-15.pgm
src/Config.h
src/Constants.hpp
src/DMS.hpp
src/GeoCoords.hpp
src/Geoid.cpp
src/Geoid.hpp
src/MGRS.hpp
src/Math.hpp
src/PolarStereographic.hpp
src/TransverseMercator.hpp
src/UTMUPS.hpp
src/Utility.hpp
src/geoid_height_wrapper.cpp
src/srtm4.c
srtm4/__init__.py
srtm4/download.py
srtm4/point.py
srtm4/raster.py
srtm4.egg-info/PKG-INFO
srtm4.egg-info/SOURCES.txt
srtm4.egg-info/dependency_links.txt
srtm4.egg-info/not-zip-safe
srtm4.egg-info/requires.txt
srtm4.egg-info/top_level.txt
tests/test_point.py
tests/test_raster.py