Metadata-Version: 2.2
Name: srtm4
Version: 1.2.5
Summary: SRTM4 elevation data reader
Home-page: https://github.com/cmla/srtm4
Author: Carlo de Franchis, Enric Meinhardt, Gabriele Facciolo
Author-email: carlo.de-franchis@ens-cachan.fr
Requires-Python: >=2.7
Requires-Dist: filelock
Requires-Dist: numpy
Requires-Dist: requests
Provides-Extra: test
Requires-Dist: pytest; extra == "test"
Requires-Dist: pytest-cov; extra == "test"
Provides-Extra: crop
Requires-Dist: rasterio; extra == "crop"
Requires-Dist: pyproj>=3.0; extra == "crop"
Requires-Dist: affine; extra == "crop"
Dynamic: author
Dynamic: author-email
Dynamic: description
Dynamic: description-content-type
Dynamic: home-page
Dynamic: provides-extra
Dynamic: requires-dist
Dynamic: requires-python
Dynamic: summary
